{"components_shadow.md":"CMZPnE3O","components_card.md":"Bn3AYpn3","css-util.md":"BnqTxzsw","components_icon.md":"T8ASiRqR","reset.md":"BZpaHh95","components_tooltip.md":"B8Hoi9hX","components_image.md":"DEAac-uN","index.md":"BVnNhXtP","usage.md":"CeCST6vA","components_checkbox.md":"DEjwSIOO","components_table.md":"kll9dzFd","components_collapse.md":"YAVT5ZVj","components_form.md":"BkP0_uDx","components_tabbar.md":"BisLeJyu","components_descriptionpanel.md":"pDbYxz6q","components_tabs.md":"Cxbp3Dik","components_directives.md":"Df9WrPk4","components_polygon.md":"BiGq1sii","components_message.md":"6z_iujv0","components_progress.md":"DESUJsos","components_switch.md":"B9tI2kuO","components_input.md":"ml1tp4ko","components_loading.md":"bvW6tLys","components_button.md":"CjfyxYkw","components_radio.md":"CEkPlh4o","components_qrcode.md":"CUns0Nzg","components_container.md":"zncjtadU"}
